README.txt
setup.cfg
setup.py
docs/HISTORY.txt
docs/INSTALL.txt
docs/LICENSE.GPL
docs/LICENSE.txt
easyshop/__init__.py
easyshop.shipping.egg-info/PKG-INFO
easyshop.shipping.egg-info/SOURCES.txt
easyshop.shipping.egg-info/dependency_links.txt
easyshop.shipping.egg-info/entry_points.txt
easyshop.shipping.egg-info/namespace_packages.txt
easyshop.shipping.egg-info/not-zip-safe
easyshop.shipping.egg-info/requires.txt
easyshop.shipping.egg-info/top_level.txt
easyshop/shipping/__init__.py
easyshop/shipping/configure.zcml
easyshop/shipping/profiles.zcml
easyshop/shipping/tests.py
easyshop/shipping/adapters/__init__.py
easyshop/shipping/adapters/configure.zcml
easyshop/shipping/adapters/shipping_method_management.py
easyshop/shipping/adapters/shipping_price_management.py
easyshop/shipping/browser/__init__.py
easyshop/shipping/browser/configure.zcml
easyshop/shipping/browser/shipping_method.pt
easyshop/shipping/browser/shipping_method.py
easyshop/shipping/browser/shipping_methods.pt
easyshop/shipping/browser/shipping_methods.py
easyshop/shipping/browser/shipping_price.pt
easyshop/shipping/browser/shipping_price.py
easyshop/shipping/browser/shipping_prices.pt
easyshop/shipping/browser/shipping_prices.py
easyshop/shipping/content/__init__.py
easyshop/shipping/content/containers.py
easyshop/shipping/content/shipping_method.py
easyshop/shipping/content/shipping_price.py
easyshop/shipping/profiles/default/factorytool.xml
easyshop/shipping/profiles/default/types.xml
easyshop/shipping/profiles/default/workflows.xml
easyshop/shipping/profiles/default/types/ShippingMethod.xml
easyshop/shipping/profiles/default/types/ShippingMethodsContainer.xml
easyshop/shipping/profiles/default/types/ShippingPrice.xml
easyshop/shipping/profiles/default/types/ShippingPricesContainer.xml